<virtual-sensor name="ETZG_Camera_from_BigBinary_scaled" priority="10" >
    <processing-class>
        <class-name>gsn.vsensor.FileGetterVirtualSensor</class-name>
        <unique-timestamps>false</unique-timestamps>
        <init-params>
            <param name="timestamp_to_string">MODIFICATIONTIME</param>
            <param name="jpeg_scaled">JPEG_SCALED</param>
            <param name="file_type">jpeg</param>
        </init-params>
        <output-structure>
            <field name="MODIFICATIONTIME_STRING" type="VARCHAR(30)" />
            <field name="JPEG_SCALED" type="binary:image/jpeg" />
        </output-structure>
    </processing-class>
    <description>camera picture from ETZG deployment as thumbnail</description>
    <life-cycle pool-size="10" />
    <addressing />
    <storage history-size="1"/>
    <streams>
        <stream name="data">
            <source alias="source" storage-size="1" sampling-rate="1">
                <address wrapper="local">
                    <predicate key="query">select MODIFICATIONTIME, RELATIVEFILE, STORAGEDIRECTORY from ETZG_BigBinary_1515 where RELATIVEFILE like 'camera1/%' and STORAGEDIRECTORY like '%etzg/'</predicate>
                </address>
                <query> select MODIFICATIONTIME, concat(STORAGEDIRECTORY,RELATIVEFILE) as FILE from wrapper</query>
            </source>
            <query> select * from source </query>
        </stream>
    </streams>
</virtual-sensor>
