<virtual-sensor name="Thur_CoreStationStatus__1950" priority="10" >
    <processing-class>
        <class-name>gsn.vsensor.BridgeVirtualSensorPermasense</class-name>
        <unique-timestamps>false</unique-timestamps>
        <output-structure>
            <field name="DEVICE_ID" type="INTEGER" />
            <field name="GENERATION_TIME" type="BIGINT" unit="unixtime" />
            <field name="TIMESTAMP" type="BIGINT" unit="unixtime" />
            <field name="V_PV" type="INTEGER" unit="mv"/>
            <field name="I_PV" type="INTEGER" unit="µa"/>
            <field name="V_12BAT" type="INTEGER" unit="mv"/>
            <field name="I_V12DC_EXT" type="INTEGER" unit="µa"/>
            <field name="V12DC_IN" type="INTEGER" unit="mv"/>
            <field name="I_V12DC_IN" type="INTEGER" unit="µa"/>
            <field name="VCC_5_0" type="INTEGER" unit="mv"/>
            <field name="VCC_NODE" type="INTEGER" unit="mv"/>
            <field name="I_VCC_NODE" type="INTEGER" unit="µa"/>
            <field name="VCC_4_2" type="INTEGER" unit="mv"/>
        </output-structure>
    </processing-class>
    <description>show status information of the CoreStations from the Thur deployment</description>
    <life-cycle pool-size="10" />
    <addressing>
        <predicate key="type">PermaSense Thur deployment</predicate>
        <predicate key="LATITUDE">47.589889</predicate>
        <predicate key="LONGITUDE">8.773874</predicate>
    </addressing>
    <storage />
    <streams>
        <stream name="data1">
            <source alias="source" storage-size="1" sampling-rate="1">
                <address wrapper="backlog">
                    <predicate key="remote-connection">permasense-thur-bs01.ethz.ch:9003</predicate>
                    <predicate key="plugin-classname">gsn.wrappers.backlog.plugins.CoreStationStatusPlugin</predicate>
                </address>
                <query> select * from wrapper </query>
            </source>
            <query> select * from source </query>
        </stream>
    </streams>
</virtual-sensor>
